parquet_csv/__init__.py
parquet_csv/parquet_to_csv.py
parquet_csv-0.2.0.dist-info/entry_points.txt
parquet_csv-0.2.0.dist-info/LICENSE
parquet_csv-0.2.0.dist-info/WHEEL
parquet_csv-0.2.0.dist-info/METADATA
parquet_csv-0.2.0.dist-info/RECORD
